odoo/addons/sale_order_product_assortment_quick/README.rst
odoo/addons/sale_order_product_assortment_quick/__init__.py
odoo/addons/sale_order_product_assortment_quick/__manifest__.py
odoo/addons/sale_order_product_assortment_quick/i18n/es.po
odoo/addons/sale_order_product_assortment_quick/i18n/it.po
odoo/addons/sale_order_product_assortment_quick/i18n/sale_order_product_assortment_quick.pot
odoo/addons/sale_order_product_assortment_quick/models/__init__.py
odoo/addons/sale_order_product_assortment_quick/models/sale_order.py
odoo/addons/sale_order_product_assortment_quick/readme/CONFIGURE.rst
odoo/addons/sale_order_product_assortment_quick/readme/CONTRIBUTORS.rst
odoo/addons/sale_order_product_assortment_quick/readme/DESCRIPTION.rst
odoo/addons/sale_order_product_assortment_quick/readme/USAGE.rst
odoo/addons/sale_order_product_assortment_quick/static/description/icon.png
odoo/addons/sale_order_product_assortment_quick/static/description/index.html
odoo/addons/sale_order_product_assortment_quick/tests/__init__.py
odoo/addons/sale_order_product_assortment_quick/tests/test_sale_order_product_assortment_quick.py
odoo14_addon_sale_order_product_assortment_quick-14.0.1.0.1.dev7.dist-info/METADATA
odoo14_addon_sale_order_product_assortment_quick-14.0.1.0.1.dev7.dist-info/WHEEL
odoo14_addon_sale_order_product_assortment_quick-14.0.1.0.1.dev7.dist-info/top_level.txt
odoo14_addon_sale_order_product_assortment_quick-14.0.1.0.1.dev7.dist-info/RECORD
