Metadata-Version: 2.1
Name: odoo14-addon-sale-order-product-assortment-quick
Version: 14.0.1.0.1.dev7
Summary: Bridge module between sale_order_product_assortment and sale_quick
Home-page: https://github.com/OCA/sale-workflow
Author: PyTech SRL, Ooops404, Odoo Community Association (OCA)
Author-email: support@odoo-community.org
License: AGPL-3
Platform: UNKNOWN
Classifier: Programming Language :: Python
Classifier: Framework :: Odoo
Classifier: Framework :: Odoo :: 14.0
Classifier: License :: OSI Approved :: GNU Affero General Public License v3
Requires-Python: >=3.6
Requires-Dist: odoo14-addon-sale-order-product-assortment
Requires-Dist: odoo14-addon-sale-quick
Requires-Dist: odoo <14.1dev,>=14.0a
